moncreneau/__init__.py
moncreneau/error.py
moncreneau/http_client.py
moncreneau/resources/__init__.py
moncreneau/resources/appointments.py
moncreneau/resources/departments.py
moncreneau-2.1.0.dist-info/LICENSE
moncreneau-2.1.0.dist-info/METADATA
moncreneau-2.1.0.dist-info/WHEEL
moncreneau-2.1.0.dist-info/top_level.txt
moncreneau-2.1.0.dist-info/RECORD
