Metadata-Version: 2.1
Name: moncreneau
Version: 2.1.0
Summary: Official Moncreneau API client for Python
Home-page: https://github.com/nbsidiki/moncreneau-python
Author: Moncreneau
Author-email: moncreneau.rdv@gmail.com
Keywords: moncreneau api client appointments booking
Classifier: Development Status :: 5 - Production/Stable
Classifier: Intended Audience :: Developers
Classifier: License :: OSI Approved :: MIT License
Classifier: Programming Language :: Python :: 3
Classifier: Programming Language :: Python :: 3.7
Classifier: Programming Language :: Python :: 3.8
Classifier: Programming Language :: Python :: 3.9
Classifier: Programming Language :: Python :: 3.10
Classifier: Programming Language :: Python :: 3.11
Requires-Python: >=3.7
License-File: LICENSE
Requires-Dist: requests>=2.28.0
